APP_Cadastro_Pessoa_Endereco/setup.py
APP_Cadastro_Pessoa_Endereco/APP_PessoaEdereco/main.py
APP_Cadastro_Pessoa_Endereco/APP_PessoaEdereco/controller/Endereco.py
APP_Cadastro_Pessoa_Endereco/APP_PessoaEdereco/controller/Pessoa.py
APP_Cadastro_Pessoa_Endereco/APP_PessoaEdereco/controller/__initi__.py
APP_Cadastro_Pessoa_Endereco/APP_PessoaEdereco/controller/generic.py
APP_Cadastro_Pessoa_Endereco/APP_PessoaEdereco/model/__init__.py
APP_Cadastro_Pessoa_Endereco/APP_PessoaEdereco/model/dto.py
APP_Cadastro_Pessoa_Endereco/APP_PessoaEdereco/model/models.py
APP_Cadastro_Pessoa_Endereco/APP_PessoaEdereco/repository/__init__.py
APP_Cadastro_Pessoa_Endereco/APP_PessoaEdereco/repository/base.py
APP_Cadastro_Pessoa_Endereco/APP_PessoaEdereco/service/__init__.py
APP_Cadastro_Pessoa_Endereco/APP_PessoaEdereco/service/base.py
APP_Cadastro_Pessoa_Endereco/APP_PessoaEdereco/test/tests.py
APP_Cadastro_Pessoa_Endereco/APP_PessoaEdereco/util/__init__.py
APP_Cadastro_Pessoa_Endereco/APP_PessoaEdereco/util/database.py
libpessoaendereco-0.1.0.dist-info/METADATA
libpessoaendereco-0.1.0.dist-info/WHEEL
libpessoaendereco-0.1.0.dist-info/top_level.txt
libpessoaendereco-0.1.0.dist-info/RECORD
