Metadata-Version: 2.4
Name: libPessoaEndereco
Version: 0.1.0
Summary: Biblioteca de criação e leitura de pessoas e enderecos
Author-email: Lucas <lucas2607.gomes@gmail.com>
Project-URL: Homepage, https://github.com/LucasMarianiG/PessoaEndereco-lib.git
Project-URL: Issues, https://github.com/LucasMarianiG/PessoaEndereco-lib.git/issues
Classifier: Programming Language :: Python :: 3
Classifier: License :: OSI Approved :: MIT License
Classifier: Operating System :: OS Independent
Requires-Python: >=3.8
Requires-Dist: sqlmodel
